pypeeringmanager/__init__.py
pypeeringmanager/core/__init__.py
pypeeringmanager/core/api.py
pypeeringmanager/core/app.py
pypeeringmanager/models/__init__.py
pypeeringmanager/models/bgp.py
pypeeringmanager/models/devices.py
pypeeringmanager/models/extras.py
pypeeringmanager/models/messaging.py
pypeeringmanager/models/net.py
pypeeringmanager/models/peering.py
pypeeringmanager/models/peeringdb.py
pypeeringmanager-1.2.0.dist-info/licenses/LICENSE
pypeeringmanager-1.2.0.dist-info/METADATA
pypeeringmanager-1.2.0.dist-info/WHEEL
pypeeringmanager-1.2.0.dist-info/top_level.txt
pypeeringmanager-1.2.0.dist-info/RECORD
