Metadata-Version: 2.4
Name: pypeeringmanager
Version: 1.2.0
Summary: Peering-Manager API client library
Home-page: https://github.com/vista-/pypeeringmanager
Author: vista
Author-email: vista@birb.network
License: Apache2
Keywords: peering-manager,peeringmanager,network-automation
Classifier: Intended Audience :: Developers
Classifier: Development Status :: 3 - Alpha
Classifier: License :: OSI Approved :: Apache Software License
Classifier: Programming Language :: Python :: 3
Classifier: Programming Language :: Python :: 2
License-File: LICENSE
Requires-Dist: pynetbox>=6.1.3
Dynamic: license-file
